{
  "name": "Maddening Hex",
  "type": "feat",
  "system": {
    "description": {
      "value": "<p>You can have the target of your <em>warlock's hex</em> take mental damage instead of void damage. You must select the type of damage when you cast the spell.</p>"
    },
    "rules": [],
    "_migration": {
      "version": 0.88,
      "lastMigration": null
    },
    "slug": "warlock-maddening-hex",
    "traits": {
      "otherTags": [],
      "value": [
        "warlock"
      ],
      "rarity": "common"
    },
    "publication": {
      "title": "",
      "authors": "",
      "license": "OGL",
      "remaster": false
    },
    "level": {
      "value": 8
    },
    "category": "class",
    "onlyLevel1": false,
    "maxTakable": 1,
    "actionType": {
      "value": "passive"
    },
    "actions": {
      "value": null
    },
    "prerequisites": {
      "value": [
        {
          "value": "warlock's hex"
        }
      ]
    }
  },
  "_id": "Z02Fw8FbWWANvP9S",
  "img": "icons/magic/symbols/runes-star-pentagon-magenta.webp",
  "_key": "!items!Z02Fw8FbWWANvP9S"
}
